[
  {
    "follower": "edm_party",
    "followee": "unverified_8"
  },
  {
    "follower": "cpop_fan",
    "followee": "fb_only_locked_5"
  },
  {
    "follower": "kpopgirl",
    "followee": "indie_cpop"
  },
  {
    "follower": "local_inactive_6",
    "followee": "rap_hiphop_dance"
  },
  {
    "follower": "local_active_4",
    "followee": "vpop_cpop_pop"
  },
  {
    "follower": "locked_indie_jazz",
    "followee": "local_inactive_5"
  },
  {
    "follower": "fb_only_unverified_2",
    "followee": "local_locked_2"
  },
  {
    "follower": "premium_y",
    "followee": "banned_jazz_dance"
  },
  {
    "follower": "rock_and_roll",
    "followee": "local_email_verified_8"
  },
  {
    "follower": "vpop_cpop_pop",
    "followee": "moderator_h"
  },
  {
    "follower": "fb_only_active_3",
    "followee": "google_only_active_3"
  },
  {
    "follower": "indie_rock",
    "followee": "jazz_addict"
  },
  {
    "follower": "cpop_fanatic",
    "followee": "premium_p"
  },
  {
    "follower": "local_email_verified",
    "followee": "fb_only_unverified"
  },
  {
    "follower": "metalhead",
    "followee": "kpop_idol"
  },
  {
    "follower": "inactive_17",
    "followee": "jpop_addict"
  },
  {
    "follower": "google_only_locked_2",
    "followee": "hiphop_rap_vpop_2"
  },
  {
    "follower": "indie_rock",
    "followee": "moderator_h"
  },
  {
    "follower": "rock_guy_2",
    "followee": "google_only_locked"
  },
  {
    "follower": "active_pop_cpop",
    "followee": "locked_jazz"
  },
  {
    "follower": "fb_only_inactive_2",
    "followee": "fb_only_banned_2"
  },
  {
    "follower": "old_school",
    "followee": "moderator_h"
  },
  {
    "follower": "pop_kpop_jpop",
    "followee": "local_email_unverified_7"
  },
  {
    "follower": "jazz_indie_cpop",
    "followee": "local_locked_2"
  },
  {
    "follower": "tamil_kpop_jpop",
    "followee": "local_email_unverified_8"
  },
  {
    "follower": "metalhead",
    "followee": "vpop_cpop_jpop"
  },
  {
    "follower": "moderator_h",
    "followee": "fb_only_locked_6"
  },
  {
    "follower": "inactive_rock",
    "followee": "fb_only_active_3"
  },
  {
    "follower": "fb_only_inactive_4",
    "followee": "rap_hiphop_indie"
  },
  {
    "follower": "guest101",
    "followee": "unverified_43"
  },
  {
    "follower": "chaam",
    "followee": "user5500"
  },
  {
    "follower": "pop_dance_rock",
    "followee": "cpop_fanatic"
  },
  {
    "follower": "vip_user_33",
    "followee": "hiphop_nation"
  },
  {
    "follower": "fb_only_active",
    "followee": "banned_rap_hiphop"
  },
  {
    "follower": "premium_v",
    "followee": "google_only_banned"
  },
  {
    "follower": "rock_guy_2",
    "followee": "indie_rock"
  },
  {
    "follower": "local_email_unverified_9",
    "followee": "fb_only_inactive_2"
  },
  {
    "follower": "tamil_kpop_jpop",
    "followee": "fb_only_active_2"
  },
  {
    "follower": "active_pop_cpop",
    "followee": "user8899"
  },
  {
    "follower": "vpop_cpop_pop",
    "followee": "jazz_rap_rock"
  },
  {
    "follower": "chill_vibes",
    "followee": "local_inactive_7"
  },
  {
    "follower": "vip_user_33",
    "followee": "cpop_fan"
  },
  {
    "follower": "indie_rock_pop_2",
    "followee": "locked_hiphop_pop"
  },
  {
    "follower": "local_no_genres_2",
    "followee": "unverified_8"
  },
  {
    "follower": "rap_hiphop_dance",
    "followee": "locked_indie_jazz"
  },
  {
    "follower": "banned_cpop_kpop",
    "followee": "chill_vibes"
  },
  {
    "follower": "mixed_genres",
    "followee": "kpop_stans"
  },
  {
    "follower": "contributor_0",
    "followee": "active_pop_cpop"
  },
  {
    "follower": "rap_hiphop_jazz",
    "followee": "old_school"
  },
  {
    "follower": "pop_hiphop_rap",
    "followee": "fb_only_unverified"
  },
  {
    "follower": "fb_only_inactive_6",
    "followee": "indie_cpop"
  },
  {
    "follower": "unverified_43",
    "followee": "kpop_bias"
  },
  {
    "follower": "fb_only_inactive_5",
    "followee": "locked_tamil_dance"
  },
  {
    "follower": "inactive_17",
    "followee": "banned_cpop_kpop"
  },
  {
    "follower": "banned_cpop_kpop",
    "followee": "local_unverified_4"
  },
  {
    "follower": "local_email_unverified_5",
    "followee": "banned_dance_rock"
  },
  {
    "follower": "musiclover01",
    "followee": "locked_jazz"
  },
  {
    "follower": "local_unverified",
    "followee": "jazz_vpop_indie"
  },
  {
    "follower": "mixed_genres",
    "followee": "indie_vpop_dance"
  },
  {
    "follower": "local_email_verified_6",
    "followee": "tamil_rock_mix"
  },
  {
    "follower": "fb_only_locked_4",
    "followee": "hiphopking"
  },
  {
    "follower": "jazz_vpop_indie",
    "followee": "google_only_active_2"
  },
  {
    "follower": "google_only_active_3",
    "followee": "user8899"
  },
  {
    "follower": "locked_hiphop_pop",
    "followee": "jazz_indie_cpop"
  },
  {
    "follower": "local_inactive_8",
    "followee": "fb_only_locked_3"
  },
  {
    "follower": "fb_only_banned_2",
    "followee": "coder_pop"
  },
  {
    "follower": "local_unverified_2",
    "followee": "user7916"
  },
  {
    "follower": "local_unverified_2",
    "followee": "pop_chill"
  },
  {
    "follower": "moderator_h",
    "followee": "local_email_verified"
  },
  {
    "follower": "metalhead",
    "followee": "fb_only_banned"
  },
  {
    "follower": "local_email_verified_2",
    "followee": "google_only_locked"
  },
  {
    "follower": "local_inactive_230",
    "followee": "local_unverified"
  },
  {
    "follower": "indie_soul",
    "followee": "local_locked_2"
  },
  {
    "follower": "metal_mania",
    "followee": "local_email_unverified_7"
  },
  {
    "follower": "pop_dance_rock",
    "followee": "fb_only_locked_6"
  },
  {
    "follower": "pop_vpop_kpop_4",
    "followee": "fb_only_locked_5"
  },
  {
    "follower": "local_inactive_6",
    "followee": "premium_v"
  },
  {
    "follower": "old_school",
    "followee": "user3100"
  },
  {
    "follower": "premium_p",
    "followee": "kpop_cpop_vip"
  },
  {
    "follower": "jazz_vpop_indie",
    "followee": "local_email_verified_6"
  },
  {
    "follower": "banned_vpop",
    "followee": "local_email_unverified_8"
  },
  {
    "follower": "musiclover01",
    "followee": "rock_guy_2"
  },
  {
    "follower": "moderator_h",
    "followee": "hiphop_rap_vpop_2"
  },
  {
    "follower": "google_only_active_4",
    "followee": "local_locked_4"
  },
  {
    "follower": "fb_only_banned_4",
    "followee": "fb_only_inactive_5"
  },
  {
    "follower": "jpop_lover",
    "followee": "fb_only_locked_5"
  },
  {
    "follower": "chaam",
    "followee": "fb_only_banned_4"
  },
  {
    "follower": "rap_hiphop_dance",
    "followee": "contributor_8"
  },
  {
    "follower": "moderator_h",
    "followee": "rap_hiphop_indie"
  },
  {
    "follower": "local_unverified_2",
    "followee": "local_email_unverified_8"
  },
  {
    "follower": "jazz_rap_rock",
    "followee": "kpop_stans"
  },
  {
    "follower": "popstar",
    "followee": "user5500"
  },
  {
    "follower": "trance_fan",
    "followee": "fb_only_locked_2"
  },
  {
    "follower": "world_jazz",
    "followee": "popstar"
  },
  {
    "follower": "inactive_4",
    "followee": "jazz_rap_rock"
  },
  {
    "follower": "local_unverified",
    "followee": "fb_only_indie"
  },
  {
    "follower": "local_active_238",
    "followee": "local_unverified"
  },
  {
    "follower": "local_email_verified_7",
    "followee": "jpop_addict"
  },
  {
    "follower": "local_inactive_230",
    "followee": "fb_only_active_2"
  },
  {
    "follower": "banned_jazz_pop",
    "followee": "indie_soul"
  },
  {
    "follower": "indie_soul",
    "followee": "popstar"
  },
  {
    "follower": "local_locked_4",
    "followee": "local_active_238"
  },
  {
    "follower": "coder_hiphop",
    "followee": "metal_mania"
  },
  {
    "follower": "local_inactive_5",
    "followee": "pop_rock_indie"
  },
  {
    "follower": "local_inactive_5",
    "followee": "banned_dance_rock"
  },
  {
    "follower": "coder_hiphop",
    "followee": "active_pop_cpop"
  },
  {
    "follower": "local_email_unverified_8",
    "followee": "fb_only_inactive_2"
  },
  {
    "follower": "tamil_kpop",
    "followee": "vpop_cpop_pop"
  },
  {
    "follower": "guest101",
    "followee": "user8899"
  },
  {
    "follower": "guest101",
    "followee": "mixed_genres"
  },
  {
    "follower": "hiphop_nation",
    "followee": "local_locked_3"
  },
  {
    "follower": "local_email_unverified_8",
    "followee": "pop_chill"
  },
  {
    "follower": "google_only_banned",
    "followee": "locked_tamil_dance"
  },
  {
    "follower": "musiclover01",
    "followee": "banned_tamil_pop_2"
  },
  {
    "follower": "pop_kpop_jpop",
    "followee": "banned_dance_rock"
  },
  {
    "follower": "fb_only_banned_3",
    "followee": "google_only_active_3"
  },
  {
    "follower": "fb_only_locked_2",
    "followee": "banned_vpop"
  },
  {
    "follower": "fb_only_locked_2",
    "followee": "local_email_unverified_5"
  },
  {
    "follower": "coder_hiphop",
    "followee": "pop_dancemix"
  },
  {
    "follower": "jpop_indie_rock",
    "followee": "locked_indie_jazz"
  },
  {
    "follower": "inactive_17",
    "followee": "banned_tamil_pop_2"
  },
  {
    "follower": "vpop_fan",
    "followee": "jazz_indie_cpop"
  },
  {
    "follower": "tamil_rap_mix_2",
    "followee": "edm_party"
  },
  {
    "follower": "fb_only_locked_5",
    "followee": "premium_v"
  },
  {
    "follower": "fb_only_inactive",
    "followee": "local_email_unverified_6"
  },
  {
    "follower": "fb_only_locked_6",
    "followee": "jazz_rap_rock"
  },
  {
    "follower": "fb_only_inactive_6",
    "followee": "local_no_genres"
  },
  {
    "follower": "fb_only_locked_6",
    "followee": "kpop_jpop_tamil"
  },
  {
    "follower": "old_school",
    "followee": "vip_user_69"
  },
  {
    "follower": "kpop_stans",
    "followee": "indie_rock"
  },
  {
    "follower": "local_inactive_8",
    "followee": "fb_only_locked_6"
  },
  {
    "follower": "user7916",
    "followee": "rnb_queen"
  },
  {
    "follower": "hiphop_rap_rock",
    "followee": "kpop_stans"
  },
  {
    "follower": "local_inactive_5",
    "followee": "kpop_cpop_vip"
  },
  {
    "follower": "pop_dancemix",
    "followee": "moderator_t"
  },
  {
    "follower": "local_inactive_7",
    "followee": "local_active_4"
  },
  {
    "follower": "local_unverified_4",
    "followee": "indie_soul"
  },
  {
    "follower": "vpop_fan",
    "followee": "metalhead"
  },
  {
    "follower": "fb_only_inactive",
    "followee": "rockfanatic"
  },
  {
    "follower": "fb_only_active",
    "followee": "local_unverified_4"
  },
  {
    "follower": "rap_hiphop_indie",
    "followee": "jazz_indie_cpop"
  },
  {
    "follower": "vpop_only",
    "followee": "unverified_8"
  },
  {
    "follower": "local_no_genres_2",
    "followee": "metal_mania"
  },
  {
    "follower": "trance_fan",
    "followee": "fb_only_banned_4"
  },
  {
    "follower": "local_email_unverified_8",
    "followee": "kpop_stans"
  },
  {
    "follower": "fb_only_active_3",
    "followee": "local_email_unverified_6"
  },
  {
    "follower": "fb_only_inactive_4",
    "followee": "premium_p"
  },
  {
    "follower": "local_email_verified_6",
    "followee": "local_inactive_8"
  },
  {
    "follower": "fb_only_unverified",
    "followee": "old_school"
  },
  {
    "follower": "jazz_vpop_indie",
    "followee": "kpop_tamil_hiphop"
  },
  {
    "follower": "fb_only_locked_4",
    "followee": "trance_fan"
  },
  {
    "follower": "active_pop_cpop",
    "followee": "local_email_verified_7"
  },
  {
    "follower": "tamil_kpop",
    "followee": "popstar"
  },
  {
    "follower": "indie_soul",
    "followee": "jazz_rap_rock"
  },
  {
    "follower": "google_only_active_4",
    "followee": "local_email_unverified_9"
  },
  {
    "follower": "musiclover01",
    "followee": "jpop_lover"
  },
  {
    "follower": "local_email_verified_8",
    "followee": "vip_user_69"
  },
  {
    "follower": "locked_tamil_dance",
    "followee": "unverified_8"
  },
  {
    "follower": "local_email_verified_7",
    "followee": "indie_soul"
  },
  {
    "follower": "folk_guy",
    "followee": "chaam"
  },
  {
    "follower": "rock_guy_2",
    "followee": "banned_cpop_kpop"
  },
  {
    "follower": "fb_only_locked_4",
    "followee": "jpop_addict"
  },
  {
    "follower": "unverified_3",
    "followee": "fb_only_inactive_6"
  },
  {
    "follower": "google_only_active_2",
    "followee": "jazz_vpop_fan"
  },
  {
    "follower": "fb_only_locked_2",
    "followee": "vip_user_33"
  },
  {
    "follower": "old_school",
    "followee": "locked_indie_jazz"
  },
  {
    "follower": "user3100",
    "followee": "chill_vibes"
  },
  {
    "follower": "pop_dancemix",
    "followee": "fb_only_inactive_6"
  },
  {
    "follower": "fb_only_banned_5",
    "followee": "fb_only_inactive"
  },
  {
    "follower": "fb_only_banned_3",
    "followee": "indie_cpop"
  },
  {
    "follower": "local_email_verified",
    "followee": "fb_only_locked"
  },
  {
    "follower": "vpop_indie_pop",
    "followee": "google_only_banned"
  },
  {
    "follower": "local_email_verified_6",
    "followee": "kpop_tamil_hiphop"
  },
  {
    "follower": "banned_jazz_dance",
    "followee": "banned_tamil_pop"
  },
  {
    "follower": "pop_dancemix",
    "followee": "hiphop_nation"
  },
  {
    "follower": "rap_hiphop_jazz",
    "followee": "banned_tamil_pop_2"
  },
  {
    "follower": "tamil_kpop",
    "followee": "tamil_kpop_jpop"
  },
  {
    "follower": "banned_tamil_pop_2",
    "followee": "jpop_lover"
  },
  {
    "follower": "fb_only_banned_2",
    "followee": "fb_only_indie"
  },
  {
    "follower": "vip_user_33",
    "followee": "premium_y"
  },
  {
    "follower": "hiphopking",
    "followee": "rap_hiphop_dance"
  },
  {
    "follower": "tamil_kpop",
    "followee": "banned_tamil_pop"
  },
  {
    "follower": "fb_only_inactive",
    "followee": "local_inactive_8"
  },
  {
    "follower": "indie_cpop",
    "followee": "local_email_verified_2"
  },
  {
    "follower": "fb_only_unverified_2",
    "followee": "unverified_9"
  },
  {
    "follower": "tamil_kpop",
    "followee": "google_only_locked"
  },
  {
    "follower": "rock_guy_2",
    "followee": "guest101"
  },
  {
    "follower": "pop_kpop_jpop",
    "followee": "hiphop_rap_rock"
  },
  {
    "follower": "jazz_vpop_fan",
    "followee": "local_no_genres"
  },
  {
    "follower": "google_only_banned",
    "followee": "tamil_kpop_jpop"
  },
  {
    "follower": "user7916",
    "followee": "locked_indie_jazz"
  },
  {
    "follower": "tamil_kpop_jpop",
    "followee": "unverified_43"
  },
  {
    "follower": "chaam",
    "followee": "local_active_238"
  },
  {
    "follower": "locked_indie_jazz",
    "followee": "google_only_banned"
  },
  {
    "follower": "local_active_238",
    "followee": "local_active_3"
  },
  {
    "follower": "fb_only_locked",
    "followee": "fb_only_locked_5"
  },
  {
    "follower": "kpop_tamil_hiphop",
    "followee": "user7916"
  },
  {
    "follower": "local_email_verified_7",
    "followee": "local_email_verified"
  },
  {
    "follower": "local_locked_4",
    "followee": "world_jazz"
  },
  {
    "follower": "tamil_kpop",
    "followee": "premium_v"
  },
  {
    "follower": "indie_vpop_dance",
    "followee": "jazz_addict"
  },
  {
    "follower": "fb_only_inactive_6",
    "followee": "local_banned"
  },
  {
    "follower": "vpop_fan",
    "followee": "local_email_unverified_7"
  },
  {
    "follower": "vpop_only",
    "followee": "locked_hiphop_pop"
  },
  {
    "follower": "fb_only_banned",
    "followee": "banned_tamil_pop_2"
  },
  {
    "follower": "kpop_dance_tamil",
    "followee": "rockfanatic"
  },
  {
    "follower": "indie_rock",
    "followee": "indie_vpop_dance"
  },
  {
    "follower": "google_only_active_2",
    "followee": "google_only_locked"
  },
  {
    "follower": "old_school",
    "followee": "tamil_dance_rap"
  },
  {
    "follower": "banned_tamil_pop_2",
    "followee": "hiphop_rap_rock"
  },
  {
    "follower": "fb_only_banned_4",
    "followee": "local_email_unverified_6"
  },
  {
    "follower": "local_email_verified_7",
    "followee": "hiphopking"
  },
  {
    "follower": "fb_only_inactive_6",
    "followee": "inactive_user"
  },
  {
    "follower": "kpop_jpop_tamil",
    "followee": "banned_dance_rock"
  },
  {
    "follower": "google_only_active_3",
    "followee": "local_email_unverified_7"
  },
  {
    "follower": "banned_rap_hiphop",
    "followee": "unverified_8"
  },
  {
    "follower": "fb_only_active",
    "followee": "musiclover01"
  },
  {
    "follower": "user8899",
    "followee": "fb_only_inactive_6"
  },
  {
    "follower": "contributor_0",
    "followee": "user3100"
  },
  {
    "follower": "banned_dance_rock",
    "followee": "local_inactive_7"
  },
  {
    "follower": "pop_dance_rock",
    "followee": "musiclover01"
  },
  {
    "follower": "moderator_t",
    "followee": "local_email_unverified_5"
  },
  {
    "follower": "locked_jazz",
    "followee": "local_active_238"
  },
  {
    "follower": "kpop_tamil_hiphop",
    "followee": "jpop_addict"
  },
  {
    "follower": "chill_vibes",
    "followee": "hiphop_nation"
  },
  {
    "follower": "banned_dance_rock",
    "followee": "indie_rock"
  },
  {
    "follower": "kpop_bias",
    "followee": "local_email_unverified_9"
  },
  {
    "follower": "tamil_rock_mix",
    "followee": "fb_only_inactive_4"
  },
  {
    "follower": "local_banned",
    "followee": "locked_rock_pop"
  },
  {
    "follower": "hiphop_rap_rock",
    "followee": "local_email_unverified_6"
  },
  {
    "follower": "google_only_locked_2",
    "followee": "fb_only_locked_4"
  },
  {
    "follower": "banned_jazz_dance",
    "followee": "cpop_fan"
  },
  {
    "follower": "unverified_3",
    "followee": "cpop_fan"
  },
  {
    "follower": "jazz_vpop_indie",
    "followee": "fb_only_locked_6"
  },
  {
    "follower": "jazz_master",
    "followee": "banned_vpop"
  },
  {
    "follower": "fb_only_inactive_6",
    "followee": "vip_user_69"
  },
  {
    "follower": "local_locked_3",
    "followee": "jazz_vpop_fan"
  },
  {
    "follower": "musiclover01",
    "followee": "local_active_4"
  },
  {
    "follower": "moderator_t",
    "followee": "fb_only_banned_5"
  },
  {
    "follower": "fb_only_active_3",
    "followee": "premium_y"
  },
  {
    "follower": "local_inactive_8",
    "followee": "unverified_4"
  },
  {
    "follower": "banned_cpop_kpop",
    "followee": "metal_mania"
  },
  {
    "follower": "indie_cpop",
    "followee": "pop_rock_indie"
  },
  {
    "follower": "google_only_banned",
    "followee": "contributor_0"
  },
  {
    "follower": "contributor_0",
    "followee": "rnb_queen"
  },
  {
    "follower": "local_unverified",
    "followee": "user8899"
  },
  {
    "follower": "local_email_unverified_7",
    "followee": "pop_dancemix"
  },
  {
    "follower": "local_email_verified_7",
    "followee": "local_active_238"
  },
  {
    "follower": "indie_vpop_dance",
    "followee": "cpop_fan"
  },
  {
    "follower": "vip_user_33",
    "followee": "indie_rock_pop_2"
  },
  {
    "follower": "fb_only_locked_2",
    "followee": "local_inactive_7"
  },
  {
    "follower": "jazz_vpop_indie",
    "followee": "local_email_unverified_8"
  },
  {
    "follower": "local_unverified_3",
    "followee": "inactive_17"
  },
  {
    "follower": "local_inactive_8",
    "followee": "local_inactive_6"
  },
  {
    "follower": "banned_vpop",
    "followee": "kpop_cpop_vip"
  },
  {
    "follower": "rap_hiphop_indie",
    "followee": "hiphop_rap_vpop_2"
  },
  {
    "follower": "kpop_bias",
    "followee": "electronic_z"
  },
  {
    "follower": "fb_only_locked_4",
    "followee": "contributor_8"
  },
  {
    "follower": "fb_only_active_2",
    "followee": "banned_dance_rock"
  },
  {
    "follower": "jazz_addict",
    "followee": "metalhead"
  },
  {
    "follower": "kpopgirl",
    "followee": "indie_folk"
  },
  {
    "follower": "rap_hiphop_indie",
    "followee": "electronic_z"
  },
  {
    "follower": "indie_soul",
    "followee": "fb_only_banned_2"
  },
  {
    "follower": "indie_soul",
    "followee": "cpop_fanatic"
  },
  {
    "follower": "local_email_unverified_6",
    "followee": "local_inactive_6"
  },
  {
    "follower": "local_inactive_5",
    "followee": "google_only_active_2"
  },
  {
    "follower": "unverified_9",
    "followee": "vpop_cpop_pop"
  },
  {
    "follower": "contributor_8",
    "followee": "jazz_addict"
  },
  {
    "follower": "banned_vpop",
    "followee": "local_inactive_6"
  },
  {
    "follower": "electronic_z",
    "followee": "world_jazz"
  },
  {
    "follower": "banned_cpop_kpop",
    "followee": "locked_jazz"
  },
  {
    "follower": "chill_vibes",
    "followee": "kpop_jpop_tamil"
  },
  {
    "follower": "local_unverified_3",
    "followee": "tamil_dance_rap"
  },
  {
    "follower": "banned_cpop_kpop",
    "followee": "fb_only_unverified"
  },
  {
    "follower": "local_email_verified_8",
    "followee": "fb_only_locked_3"
  },
  {
    "follower": "indie_folk",
    "followee": "google_only_active_4"
  },
  {
    "follower": "banned_jazz_pop",
    "followee": "local_locked_4"
  },
  {
    "follower": "locked_rock_pop",
    "followee": "banned_tamil_pop"
  },
  {
    "follower": "tamil_dance_rap",
    "followee": "local_active_238"
  },
  {
    "follower": "locked_tamil_dance",
    "followee": "contributor_8"
  },
  {
    "follower": "cpop_fanatic",
    "followee": "user8899"
  },
  {
    "follower": "local_active_3",
    "followee": "local_email_verified_7"
  },
  {
    "follower": "pop_dancemix",
    "followee": "premium_y"
  },
  {
    "follower": "fb_only_inactive_3",
    "followee": "hiphop_rap_vpop_2"
  },
  {
    "follower": "local_email_unverified_7",
    "followee": "google_only_locked_3"
  },
  {
    "follower": "local_locked_3",
    "followee": "inactive_4"
  },
  {
    "follower": "fb_only_inactive_4",
    "followee": "locked_rock_pop"
  },
  {
    "follower": "fb_only_locked_3",
    "followee": "local_email_verified_8"
  },
  {
    "follower": "locked_jazz",
    "followee": "fb_only_active_3"
  },
  {
    "follower": "local_email_verified_6",
    "followee": "rock_and_roll"
  },
  {
    "follower": "local_locked_4",
    "followee": "jazz_master"
  },
  {
    "follower": "local_inactive_5",
    "followee": "user8899"
  },
  {
    "follower": "fb_only_inactive_4",
    "followee": "fb_only_locked_6"
  },
  {
    "follower": "local_active_4",
    "followee": "inactive_user"
  },
  {
    "follower": "local_email_unverified_5",
    "followee": "local_email_verified_7"
  },
  {
    "follower": "vpop_fan",
    "followee": "unverified_3"
  },
  {
    "follower": "premium_y",
    "followee": "inactive_user"
  },
  {
    "follower": "local_email_verified_2",
    "followee": "fb_only_inactive_4"
  },
  {
    "follower": "local_locked_4",
    "followee": "fb_only_inactive_6"
  },
  {
    "follower": "hiphopking",
    "followee": "local_email_unverified_9"
  },
  {
    "follower": "fb_only_unverified",
    "followee": "inactive_17"
  },
  {
    "follower": "fb_only_locked_3",
    "followee": "kpop_bias"
  },
  {
    "follower": "google_only_active_4",
    "followee": "jazz_master"
  },
  {
    "follower": "fb_only_locked",
    "followee": "local_email_unverified_5"
  },
  {
    "follower": "local_email_verified_8",
    "followee": "local_active_4"
  },
  {
    "follower": "vpop_indie_pop",
    "followee": "local_inactive_6"
  },
  {
    "follower": "fb_only_active_3",
    "followee": "local_locked_3"
  },
  {
    "follower": "banned_rap_hiphop",
    "followee": "local_unverified_3"
  },
  {
    "follower": "pop_hiphop_vpop",
    "followee": "fb_only_inactive_2"
  },
  {
    "follower": "local_email_unverified_5",
    "followee": "pop_hiphop_vpop"
  },
  {
    "follower": "local_email_verified_7",
    "followee": "pop_rock_indie"
  },
  {
    "follower": "user8899",
    "followee": "vpop_indie_pop"
  },
  {
    "follower": "jazz_master",
    "followee": "local_email_verified_2"
  },
  {
    "follower": "local_inactive_8",
    "followee": "local_email_unverified_7"
  },
  {
    "follower": "inactive_17",
    "followee": "fb_only_active_2"
  },
  {
    "follower": "banned_rap_hiphop",
    "followee": "jazz_vpop_indie"
  },
  {
    "follower": "local_active_3",
    "followee": "local_email_unverified_6"
  },
  {
    "follower": "local_locked_3",
    "followee": "banned_tamil_pop"
  },
  {
    "follower": "local_locked_3",
    "followee": "pop_hiphop_vpop"
  },
  {
    "follower": "kpop_bias",
    "followee": "unverified_4"
  },
  {
    "follower": "banned_jazz_pop",
    "followee": "unverified_43"
  },
  {
    "follower": "jpop_indie_rock",
    "followee": "fb_only_inactive_6"
  },
  {
    "follower": "local_inactive_6",
    "followee": "inactive_rock"
  },
  {
    "follower": "rap_hiphop_jazz",
    "followee": "pop_rock_indie"
  },
  {
    "follower": "moderator_t",
    "followee": "local_unverified_3"
  },
  {
    "follower": "inactive_rock",
    "followee": "user3100"
  },
  {
    "follower": "hiphop_rap_rock",
    "followee": "chill_vibes"
  },
  {
    "follower": "banned_tamil_pop",
    "followee": "fb_only_inactive_3"
  },
  {
    "follower": "local_email_verified_7",
    "followee": "trance_fan"
  },
  {
    "follower": "local_email_unverified_8",
    "followee": "local_inactive_7"
  },
  {
    "follower": "local_inactive_7",
    "followee": "local_unverified_3"
  },
  {
    "follower": "fb_only_inactive_4",
    "followee": "local_inactive_5"
  },
  {
    "follower": "inactive_rock",
    "followee": "local_email_unverified_5"
  },
  {
    "follower": "local_inactive_230",
    "followee": "pop_hiphop_vpop"
  },
  {
    "follower": "fb_only_locked_4",
    "followee": "locked_jazz"
  },
  {
    "follower": "local_inactive_7",
    "followee": "kpop_cpop_vip"
  },
  {
    "follower": "local_email_unverified_9",
    "followee": "local_locked_4"
  },
  {
    "follower": "inactive_4",
    "followee": "rap_hiphop_dance"
  },
  {
    "follower": "local_active_4",
    "followee": "local_inactive_5"
  },
  {
    "follower": "vpop_indie_pop",
    "followee": "moderator_h"
  },
  {
    "follower": "moderator_h",
    "followee": "local_locked_3"
  },
  {
    "follower": "local_locked_3",
    "followee": "user3100"
  },
  {
    "follower": "local_email_verified_8",
    "followee": "hiphop_rap_rock"
  },
  {
    "follower": "kpopgirl",
    "followee": "local_email_verified_6"
  },
  {
    "follower": "local_inactive_5",
    "followee": "jazz_vpop_indie"
  },
  {
    "follower": "user8899",
    "followee": "local_active_4"
  },
  {
    "follower": "metalhead",
    "followee": "fb_only_inactive_6"
  },
  {
    "follower": "local_email_unverified_6",
    "followee": "local_locked_4"
  },
  {
    "follower": "local_inactive_6",
    "followee": "local_inactive_8"
  },
  {
    "follower": "fb_only_active_2",
    "followee": "inactive_rock"
  },
  {
    "follower": "local_locked_2",
    "followee": "fb_only_active_3"
  },
  {
    "follower": "premium_y",
    "followee": "local_locked_3"
  },
  {
    "follower": "rap_hiphop_jazz",
    "followee": "premium_v"
  },
  {
    "follower": "local_unverified_4",
    "followee": "fb_only_locked_5"
  },
  {
    "follower": "trance_fan",
    "followee": "fb_only_locked_6"
  },
  {
    "follower": "local_email_verified",
    "followee": "rock_and_roll"
  },
  {
    "follower": "rock_and_roll",
    "followee": "local_email_unverified_5"
  },
  {
    "follower": "local_unverified_3",
    "followee": "fb_only_inactive_4"
  },
  {
    "follower": "rnb_queen",
    "followee": "fb_only_inactive_3"
  },
  {
    "follower": "user3100",
    "followee": "jazz_rap_rock"
  },
  {
    "follower": "local_email_verified_6",
    "followee": "local_locked_2"
  },
  {
    "follower": "moderator_t",
    "followee": "fb_only_locked"
  },
  {
    "follower": "unverified_4",
    "followee": "jazz_vpop_indie"
  },
  {
    "follower": "fb_only_locked_6",
    "followee": "local_email_unverified_7"
  },
  {
    "follower": "pop_hiphop_rap",
    "followee": "jazz_rap_cpop"
  },
  {
    "follower": "local_email_unverified_5",
    "followee": "indie_rock_pop_2"
  },
  {
    "follower": "local_email_verified_6",
    "followee": "google_only_active_4"
  },
  {
    "follower": "banned_jazz_pop",
    "followee": "fb_only_inactive_6"
  },
  {
    "follower": "local_email_unverified_9",
    "followee": "local_email_unverified_5"
  },
  {
    "follower": "fb_only_inactive_5",
    "followee": "fb_only_active_2"
  },
  {
    "follower": "local_email_verified_8",
    "followee": "pop_rock_indie"
  },
  {
    "follower": "local_locked_4",
    "followee": "hiphop_rap_vpop_2"
  },
  {
    "follower": "locked_jazz",
    "followee": "jazz_master"
  },
  {
    "follower": "metal_mania",
    "followee": "hiphop_nation"
  },
  {
    "follower": "local_email_verified_8",
    "followee": "pop_hiphop_vpop"
  },
  {
    "follower": "hiphopking",
    "followee": "local_email_unverified_6"
  },
  {
    "follower": "rnb_queen",
    "followee": "hiphop_rap_vpop_2"
  },
  {
    "follower": "jazz_vpop_fan",
    "followee": "local_email_unverified_9"
  },
  {
    "follower": "local_active_4",
    "followee": "fb_only_locked_5"
  },
  {
    "follower": "hiphop_rap_rock",
    "followee": "local_unverified_3"
  },
  {
    "follower": "user8899",
    "followee": "vpop_cpop_jpop"
  },
  {
    "follower": "fb_only_inactive_3",
    "followee": "fb_only_banned_4"
  },
  {
    "follower": "local_locked_3",
    "followee": "fb_only_inactive_2"
  },
  {
    "follower": "inactive_4",
    "followee": "local_locked_4"
  },
  {
    "follower": "inactive_4",
    "followee": "pop_kpop_jpop"
  },
  {
    "follower": "local_unverified_3",
    "followee": "user3100"
  },
  {
    "follower": "metalhead",
    "followee": "local_inactive_5"
  },
  {
    "follower": "premium_y",
    "followee": "local_email_unverified_5"
  },
  {
    "follower": "trance_fan",
    "followee": "hiphop_rap_rock"
  },
  {
    "follower": "pop_hiphop_vpop",
    "followee": "local_active_3"
  },
  {
    "follower": "user3100",
    "followee": "fb_only_active_2"
  },
  {
    "follower": "banned_vpop",
    "followee": "fb_only_locked_4"
  },
  {
    "follower": "fb_only_locked",
    "followee": "local_email_verified_8"
  },
  {
    "follower": "google_only_active_3",
    "followee": "fb_only_locked_4"
  },
  {
    "follower": "rap_hiphop_jazz",
    "followee": "local_inactive_8"
  },
  {
    "follower": "google_only_active_3",
    "followee": "locked_jazz"
  },
  {
    "follower": "local_email_unverified_7",
    "followee": "local_locked_3"
  },
  {
    "follower": "local_email_verified_6",
    "followee": "fb_only_inactive_5"
  },
  {
    "follower": "inactive_rock",
    "followee": "local_unverified_4"
  },
  {
    "follower": "popstar",
    "followee": "local_email_verified_7"
  },
  {
    "follower": "local_active_238",
    "followee": "user7916"
  },
  {
    "follower": "google_only_banned",
    "followee": "fb_only_inactive_5"
  },
  {
    "follower": "local_inactive_7",
    "followee": "banned_rap_hiphop"
  },
  {
    "follower": "fb_only_inactive_3",
    "followee": "local_email_unverified_8"
  },
  {
    "follower": "rnb_queen",
    "followee": "local_inactive_8"
  },
  {
    "follower": "fb_only_locked_4",
    "followee": "local_email_unverified_5"
  },
  {
    "follower": "hiphop_rap_vpop_2",
    "followee": "local_email_verified"
  },
  {
    "follower": "locked_tamil_dance",
    "followee": "fb_only_active_2"
  },
  {
    "follower": "local_locked_4",
    "followee": "premium_y"
  },
  {
    "follower": "unverified_4",
    "followee": "local_locked_3"
  },
  {
    "follower": "pop_rock_indie",
    "followee": "local_email_verified_7"
  },
  {
    "follower": "inactive_17",
    "followee": "fb_only_locked_3"
  },
  {
    "follower": "local_email_verified_6",
    "followee": "local_email_verified_2"
  },
  {
    "follower": "jpop_cpop_vpop_3",
    "followee": "local_active_4"
  },
  {
    "follower": "local_email_unverified_9",
    "followee": "inactive_17"
  },
  {
    "follower": "local_email_verified",
    "followee": "premium_v"
  },
  {
    "follower": "fb_only_inactive_5",
    "followee": "local_locked_3"
  },
  {
    "follower": "popstar",
    "followee": "rock_and_roll"
  },
  {
    "follower": "fb_only_locked_6",
    "followee": "vpop_fan"
  },
  {
    "follower": "jazz_vpop_fan",
    "followee": "fb_only_active"
  },
  {
    "follower": "jpop_cpop_vpop_3",
    "followee": "hiphop_rap_rock"
  },
  {
    "follower": "hiphopking",
    "followee": "local_email_verified_2"
  },
  {
    "follower": "banned_rap_hiphop",
    "followee": "local_email_verified_7"
  },
  {
    "follower": "local_email_verified_2",
    "followee": "rap_hiphop_jazz"
  },
  {
    "follower": "local_inactive_7",
    "followee": "local_email_verified"
  },
  {
    "follower": "moderator_t",
    "followee": "local_email_verified_2"
  },
  {
    "follower": "rockfanatic",
    "followee": "jpop_addict"
  },
  {
    "follower": "fb_only_locked_5",
    "followee": "local_email_verified"
  },
  {
    "follower": "pop_hiphop_vpop",
    "followee": "fb_only_active_2"
  },
  {
    "follower": "pop_rock_indie",
    "followee": "local_email_unverified_8"
  },
  {
    "follower": "fb_only_inactive_3",
    "followee": "unverified_4"
  },
  {
    "follower": "local_email_verified_8",
    "followee": "local_email_unverified_5"
  },
  {
    "follower": "local_active_3",
    "followee": "metal_mania"
  },
  {
    "follower": "inactive_rock",
    "followee": "hiphopking"
  },
  {
    "follower": "google_only_active_2",
    "followee": "local_active_3"
  },
  {
    "follower": "local_unverified_3",
    "followee": "user8899"
  },
  {
    "follower": "local_inactive_6",
    "followee": "vpop_fan"
  },
  {
    "follower": "fb_only_inactive_4",
    "followee": "local_email_unverified_6"
  },
  {
    "follower": "local_email_unverified_6",
    "followee": "local_active_238"
  },
  {
    "follower": "pop_dancemix",
    "followee": "inactive_rock"
  },
  {
    "follower": "local_email_verified_2",
    "followee": "jpop_addict"
  },
  {
    "follower": "inactive_17",
    "followee": "local_unverified_2"
  },
  {
    "follower": "rnb_queen",
    "followee": "fb_only_inactive_6"
  },
  {
    "follower": "fb_only_active_3",
    "followee": "user3100"
  },
  {
    "follower": "fb_only_locked_4",
    "followee": "inactive_rock"
  },
  {
    "follower": "rock_and_roll",
    "followee": "premium_y"
  },
  {
    "follower": "local_inactive_8",
    "followee": "unverified_3"
  },
  {
    "follower": "rock_guy_2",
    "followee": "fb_only_inactive_3"
  },
  {
    "follower": "jpop_rap_dance",
    "followee": "local_locked_2"
  },
  {
    "follower": "local_unverified_4",
    "followee": "local_active_4"
  },
  {
    "follower": "hiphopking",
    "followee": "local_locked_3"
  },
  {
    "follower": "jazz_master",
    "followee": "local_inactive_6"
  },
  {
    "follower": "local_inactive_6",
    "followee": "hiphopking"
  },
  {
    "follower": "hiphop_rap_rock",
    "followee": "premium_p"
  },
  {
    "follower": "local_active_238",
    "followee": "rock_and_roll"
  },
  {
    "follower": "fb_only_active",
    "followee": "fb_only_locked_4"
  },
  {
    "follower": "kpop_stans",
    "followee": "local_email_verified_7"
  },
  {
    "follower": "local_email_verified_6",
    "followee": "jpop_lover"
  },
  {
    "follower": "jpop_addict",
    "followee": "hiphop_rap_rock"
  },
  {
    "follower": "inactive_4",
    "followee": "fb_only_active_3"
  },
  {
    "follower": "local_email_unverified_7",
    "followee": "local_email_verified_8"
  },
  {
    "follower": "local_inactive_7",
    "followee": "local_email_verified_6"
  },
  {
    "follower": "local_email_unverified_6",
    "followee": "fb_only_locked_3"
  },
  {
    "follower": "local_email_verified_2",
    "followee": "fb_only_inactive_6"
  },
  {
    "follower": "rnb_queen",
    "followee": "local_email_unverified_7"
  },
  {
    "follower": "fb_only_inactive_4",
    "followee": "local_unverified"
  },
  {
    "follower": "user3100",
    "followee": "locked_tamil_dance"
  },
  {
    "follower": "rnb_queen",
    "followee": "pop_dancemix"
  },
  {
    "follower": "trance_fan",
    "followee": "inactive_rock"
  },
  {
    "follower": "locked_rock_pop",
    "followee": "local_unverified_2"
  },
  {
    "follower": "local_unverified_3",
    "followee": "google_only_locked"
  },
  {
    "follower": "local_inactive_230",
    "followee": "fb_only_locked_4"
  },
  {
    "follower": "local_email_unverified_5",
    "followee": "user8899"
  },
  {
    "follower": "fb_only_inactive_5",
    "followee": "local_email_verified_7"
  },
  {
    "follower": "local_email_unverified_5",
    "followee": "premium_y"
  },
  {
    "follower": "inactive_rock",
    "followee": "local_email_verified_6"
  },
  {
    "follower": "fb_only_inactive_6",
    "followee": "pop_kpop_jpop"
  },
  {
    "follower": "fb_only_active_2",
    "followee": "local_email_verified_6"
  },
  {
    "follower": "pop_kpop_jpop",
    "followee": "local_email_unverified_6"
  },
  {
    "follower": "user3100",
    "followee": "inactive_rock"
  },
  {
    "follower": "local_active_3",
    "followee": "local_email_verified_2"
  },
  {
    "follower": "local_active_4",
    "followee": "pop_hiphop_vpop"
  },
  {
    "follower": "local_locked_2",
    "followee": "jazz_rap_cpop"
  },
  {
    "follower": "pop_vpop_kpop_4",
    "followee": "local_inactive_5"
  },
  {
    "follower": "local_email_verified_2",
    "followee": "locked_indie_jazz"
  },
  {
    "follower": "local_inactive_5",
    "followee": "google_only_banned"
  },
  {
    "follower": "pop_rock_indie",
    "followee": "user7916"
  },
  {
    "follower": "jpop_rap_dance",
    "followee": "kpop_stans"
  },
  {
    "follower": "trance_fan",
    "followee": "local_email_verified"
  },
  {
    "follower": "metal_mania",
    "followee": "pop_dancemix"
  },
  {
    "follower": "inactive_user",
    "followee": "local_locked_3"
  },
  {
    "follower": "local_email_verified_8",
    "followee": "local_locked_2"
  },
  {
    "follower": "local_inactive_7",
    "followee": "local_active_3"
  },
  {
    "follower": "fb_only_inactive_3",
    "followee": "local_email_verified"
  },
  {
    "follower": "moderator_t",
    "followee": "local_email_verified_6"
  },
  {
    "follower": "fb_only_unverified",
    "followee": "local_unverified_4"
  },
  {
    "follower": "rap_hiphop_dance",
    "followee": "fb_only_locked_4"
  },
  {
    "follower": "local_email_verified_2",
    "followee": "local_inactive_8"
  },
  {
    "follower": "local_email_unverified_6",
    "followee": "rap_hiphop_indie"
  },
  {
    "follower": "local_email_verified_2",
    "followee": "local_inactive_7"
  },
  {
    "follower": "hiphopking",
    "followee": "local_email_verified_8"
  },
  {
    "follower": "fb_only_inactive_6",
    "followee": "local_active_4"
  },
  {
    "follower": "kpop_bias",
    "followee": "inactive_rock"
  },
  {
    "follower": "local_inactive_5",
    "followee": "fb_only_inactive_3"
  },
  {
    "follower": "local_email_verified_8",
    "followee": "fb_only_inactive_3"
  },
  {
    "follower": "inactive_rock",
    "followee": "local_active_4"
  },
  {
    "follower": "trance_fan",
    "followee": "local_inactive_8"
  },
  {
    "follower": "trance_fan",
    "followee": "local_email_unverified_7"
  },
  {
    "follower": "local_locked_4",
    "followee": "user3100"
  },
  {
    "follower": "jpop_lover",
    "followee": "local_email_verified_7"
  },
  {
    "follower": "kpop_jpop_tamil",
    "followee": "local_active_3"
  },
  {
    "follower": "fb_only_active_3",
    "followee": "trance_fan"
  },
  {
    "follower": "pop_vpop_kpop_4",
    "followee": "fb_only_active_3"
  },
  {
    "follower": "local_inactive_7",
    "followee": "rock_and_roll"
  },
  {
    "follower": "local_email_verified_7",
    "followee": "inactive_rock"
  },
  {
    "follower": "popstar",
    "followee": "local_inactive_6"
  },
  {
    "follower": "inactive_rock",
    "followee": "banned_rap_hiphop"
  },
  {
    "follower": "fb_only_locked_3",
    "followee": "google_only_banned"
  },
  {
    "follower": "fb_only_active_2",
    "followee": "local_email_verified_7"
  },
  {
    "follower": "local_inactive_6",
    "followee": "trance_fan"
  },
  {
    "follower": "pop_rock_indie",
    "followee": "rock_and_roll"
  },
  {
    "follower": "local_email_verified_7",
    "followee": "local_unverified_2"
  },
  {
    "follower": "fb_only_locked",
    "followee": "fb_only_active_3"
  },
  {
    "follower": "local_active_3",
    "followee": "local_email_verified"
  },
  {
    "follower": "moderator_t",
    "followee": "hiphop_rap_vpop_2"
  },
  {
    "follower": "jazz_vpop_indie",
    "followee": "local_unverified_3"
  },
  {
    "follower": "jazz_master",
    "followee": "fb_only_locked_4"
  },
  {
    "follower": "local_locked_4",
    "followee": "local_email_unverified_9"
  },
  {
    "follower": "fb_only_locked_3",
    "followee": "fb_only_active"
  },
  {
    "follower": "metal_mania",
    "followee": "fb_only_locked_2"
  },
  {
    "follower": "fb_only_locked_5",
    "followee": "pop_dancemix"
  },
  {
    "follower": "local_email_unverified_7",
    "followee": "local_email_verified"
  },
  {
    "follower": "unverified_4",
    "followee": "local_inactive_6"
  },
  {
    "follower": "local_email_unverified_7",
    "followee": "unverified_8"
  },
  {
    "follower": "local_email_unverified_6",
    "followee": "inactive_rock"
  },
  {
    "follower": "jpop_addict",
    "followee": "banned_vpop"
  },
  {
    "follower": "metalhead",
    "followee": "local_email_unverified_5"
  },
  {
    "follower": "banned_rap_hiphop",
    "followee": "metalhead"
  },
  {
    "follower": "locked_rock_pop",
    "followee": "fb_only_inactive_6"
  },
  {
    "follower": "local_email_unverified_6",
    "followee": "rock_guy_2"
  },
  {
    "follower": "local_inactive_5",
    "followee": "rock_and_roll"
  },
  {
    "follower": "unverified_9",
    "followee": "local_email_verified_7"
  },
  {
    "follower": "trance_fan",
    "followee": "local_email_verified_2"
  },
  {
    "follower": "local_active_3",
    "followee": "local_locked_4"
  },
  {
    "follower": "local_locked_2",
    "followee": "local_email_verified_8"
  },
  {
    "follower": "moderator_t",
    "followee": "local_email_verified_7"
  },
  {
    "follower": "inactive_17",
    "followee": "moderator_t"
  },
  {
    "follower": "local_email_verified_2",
    "followee": "local_email_verified"
  },
  {
    "follower": "fb_only_inactive_2",
    "followee": "local_active_238"
  },
  {
    "follower": "moderator_t",
    "followee": "local_email_unverified_8"
  },
  {
    "follower": "inactive_4",
    "followee": "fb_only_locked_4"
  },
  {
    "follower": "fb_only_locked_5",
    "followee": "local_unverified"
  },
  {
    "follower": "local_inactive_7",
    "followee": "pop_hiphop_rap"
  },
  {
    "follower": "user7916",
    "followee": "local_email_verified_6"
  },
  {
    "follower": "hiphopking",
    "followee": "fb_only_inactive_4"
  },
  {
    "follower": "inactive_rock",
    "followee": "fb_only_inactive_5"
  },
  {
    "follower": "local_email_verified_8",
    "followee": "local_locked_3"
  },
  {
    "follower": "local_email_verified_8",
    "followee": "pop_dance_rock"
  },
  {
    "follower": "pop_hiphop_rap",
    "followee": "local_email_verified_6"
  },
  {
    "follower": "user3100",
    "followee": "jpop_lover"
  },
  {
    "follower": "local_active_3",
    "followee": "inactive_4"
  },
  {
    "follower": "local_inactive_5",
    "followee": "local_active_3"
  },
  {
    "follower": "pop_dance_rock",
    "followee": "inactive_user"
  },
  {
    "follower": "local_unverified_4",
    "followee": "local_inactive_5"
  },
  {
    "follower": "local_email_unverified_7",
    "followee": "fb_only_inactive_3"
  },
  {
    "follower": "local_active_3",
    "followee": "fb_only_inactive_2"
  },
  {
    "follower": "local_email_verified_7",
    "followee": "fb_only_inactive_6"
  },
  {
    "follower": "local_inactive_8",
    "followee": "jpop_lover"
  },
  {
    "follower": "pop_vpop_kpop_4",
    "followee": "fb_only_locked_3"
  },
  {
    "follower": "vpop_only",
    "followee": "local_inactive_8"
  },
  {
    "follower": "local_locked_3",
    "followee": "inactive_user"
  },
  {
    "follower": "metal_mania",
    "followee": "fb_only_locked_3"
  },
  {
    "follower": "local_active_238",
    "followee": "jpop_lover"
  },
  {
    "follower": "fb_only_inactive_6",
    "followee": "fb_only_locked_3"
  },
  {
    "follower": "inactive_user",
    "followee": "local_email_unverified_7"
  },
  {
    "follower": "local_email_unverified_5",
    "followee": "local_email_verified_6"
  },
  {
    "follower": "local_active_4",
    "followee": "local_locked_3"
  },
  {
    "follower": "rap_hiphop_indie",
    "followee": "fb_only_inactive_6"
  },
  {
    "follower": "local_inactive_8",
    "followee": "local_unverified_2"
  },
  {
    "follower": "fb_only_active_2",
    "followee": "local_locked_3"
  },
  {
    "follower": "fb_only_inactive_3",
    "followee": "local_email_verified_6"
  },
  {
    "follower": "local_locked_4",
    "followee": "fb_only_inactive_3"
  },
  {
    "follower": "local_email_verified_7",
    "followee": "local_inactive_8"
  },
  {
    "follower": "fb_only_locked_3",
    "followee": "rap_hiphop_jazz"
  },
  {
    "follower": "hiphop_rap_vpop_2",
    "followee": "local_email_verified_8"
  },
  {
    "follower": "local_locked_4",
    "followee": "vpop_fan"
  },
  {
    "follower": "fb_only_locked_4",
    "followee": "rnb_queen"
  },
  {
    "follower": "pop_hiphop_vpop",
    "followee": "local_locked_4"
  },
  {
    "follower": "metalhead",
    "followee": "local_email_unverified_7"
  },
  {
    "follower": "local_email_unverified_6",
    "followee": "local_unverified_3"
  },
  {
    "follower": "local_email_verified_8",
    "followee": "local_active_3"
  },
  {
    "follower": "local_email_unverified_9",
    "followee": "local_email_verified_6"
  },
  {
    "follower": "user8899",
    "followee": "trance_fan"
  },
  {
    "follower": "inactive_rock",
    "followee": "local_email_verified"
  },
  {
    "follower": "rock_and_roll",
    "followee": "local_unverified_3"
  },
  {
    "follower": "inactive_rock",
    "followee": "local_inactive_7"
  },
  {
    "follower": "vpop_fan",
    "followee": "local_email_verified_8"
  },
  {
    "follower": "pop_hiphop_vpop",
    "followee": "local_active_4"
  },
  {
    "follower": "fb_only_inactive",
    "followee": "local_active_3"
  },
  {
    "follower": "rnb_queen",
    "followee": "local_locked_4"
  },
  {
    "follower": "pop_hiphop_rap",
    "followee": "pop_kpop_jpop"
  },
  {
    "follower": "local_inactive_6",
    "followee": "local_email_unverified_7"
  },
  {
    "follower": "local_active_3",
    "followee": "banned_tamil_pop"
  },
  {
    "follower": "local_email_verified_6",
    "followee": "fb_only_inactive_3"
  },
  {
    "follower": "inactive_4",
    "followee": "local_email_verified_2"
  },
  {
    "follower": "local_email_verified",
    "followee": "pop_vpop_kpop_4"
  },
  {
    "follower": "local_email_verified_6",
    "followee": "rock_guy_2"
  },
  {
    "follower": "inactive_user",
    "followee": "local_email_verified_6"
  },
  {
    "follower": "local_email_unverified_5",
    "followee": "metal_mania"
  },
  {
    "follower": "metal_mania",
    "followee": "unverified_4"
  },
  {
    "follower": "fb_only_inactive_6",
    "followee": "jazz_master"
  },
  {
    "follower": "fb_only_inactive_3",
    "followee": "local_email_verified_8"
  },
  {
    "follower": "hiphop_rap_vpop_2",
    "followee": "local_email_unverified_7"
  },
  {
    "follower": "local_inactive_8",
    "followee": "hiphop_rap_vpop_2"
  },
  {
    "follower": "local_locked_4",
    "followee": "local_email_verified"
  },
  {
    "follower": "inactive_user",
    "followee": "local_inactive_8"
  },
  {
    "follower": "local_email_verified_8",
    "followee": "fb_only_locked_4"
  },
  {
    "follower": "fb_only_inactive_2",
    "followee": "local_locked_4"
  },
  {
    "follower": "local_locked_4",
    "followee": "local_email_verified_7"
  },
  {
    "follower": "local_email_verified_2",
    "followee": "inactive_rock"
  },
  {
    "follower": "local_inactive_7",
    "followee": "metalhead"
  },
  {
    "follower": "inactive_user",
    "followee": "local_inactive_7"
  },
  {
    "follower": "hiphopking",
    "followee": "fb_only_inactive_2"
  },
  {
    "follower": "local_inactive_8",
    "followee": "rnb_queen"
  },
  {
    "follower": "local_email_unverified_6",
    "followee": "inactive_user"
  },
  {
    "follower": "fb_only_inactive_4",
    "followee": "local_active_3"
  },
  {
    "follower": "kpop_cpop_vip",
    "followee": "fb_only_inactive"
  },
  {
    "follower": "local_email_verified_7",
    "followee": "pop_kpop_jpop"
  },
  {
    "follower": "local_email_verified_7",
    "followee": "fb_only_locked_5"
  },
  {
    "follower": "jazz_master",
    "followee": "kpop_tamil_hiphop"
  },
  {
    "follower": "local_locked_3",
    "followee": "local_email_unverified_7"
  },
  {
    "follower": "inactive_rock",
    "followee": "local_locked_4"
  },
  {
    "follower": "moderator_h",
    "followee": "fb_only_active_2"
  },
  {
    "follower": "local_email_verified_7",
    "followee": "fb_only_inactive_4"
  },
  {
    "follower": "pop_rock_indie",
    "followee": "rock_guy_2"
  },
  {
    "follower": "inactive_user",
    "followee": "local_email_verified"
  },
  {
    "follower": "fb_only_inactive_3",
    "followee": "metal_mania"
  },
  {
    "follower": "local_email_verified_8",
    "followee": "local_email_unverified_7"
  },
  {
    "follower": "local_locked_3",
    "followee": "local_email_verified_2"
  },
  {
    "follower": "rnb_queen",
    "followee": "local_email_verified_6"
  },
  {
    "follower": "local_inactive_5",
    "followee": "unverified_4"
  },
  {
    "follower": "local_email_verified_7",
    "followee": "local_email_verified_6"
  },
  {
    "follower": "kpopgirl",
    "followee": "local_locked_4"
  },
  {
    "follower": "fb_only_inactive_5",
    "followee": "fb_only_locked_4"
  },
  {
    "follower": "local_active_4",
    "followee": "local_email_unverified_7"
  },
  {
    "follower": "banned_vpop",
    "followee": "local_email_verified_7"
  },
  {
    "follower": "kpop_cpop_vip",
    "followee": "trance_fan"
  },
  {
    "follower": "hiphop_rap_vpop_2",
    "followee": "banned_rap_hiphop"
  },
  {
    "follower": "inactive_rock",
    "followee": "popstar"
  },
  {
    "follower": "local_email_verified_8",
    "followee": "local_inactive_6"
  },
  {
    "follower": "local_locked_4",
    "followee": "fb_only_inactive_4"
  },
  {
    "follower": "local_email_unverified_6",
    "followee": "hiphopking"
  },
  {
    "follower": "fb_only_inactive_5",
    "followee": "pop_hiphop_vpop"
  },
  {
    "follower": "local_inactive_8",
    "followee": "rock_and_roll"
  },
  {
    "follower": "fb_only_active_2",
    "followee": "inactive_4"
  },
  {
    "follower": "local_unverified_2",
    "followee": "hiphop_rap_vpop_2"
  },
  {
    "follower": "local_email_verified",
    "followee": "local_locked_4"
  },
  {
    "follower": "local_inactive_7",
    "followee": "local_email_verified_2"
  },
  {
    "follower": "metal_mania",
    "followee": "local_email_verified_2"
  },
  {
    "follower": "local_email_verified_8",
    "followee": "fb_only_locked_2"
  },
  {
    "follower": "fb_only_locked_5",
    "followee": "inactive_rock"
  },
  {
    "follower": "local_active_3",
    "followee": "local_locked_2"
  },
  {
    "follower": "inactive_user",
    "followee": "local_active_4"
  },
  {
    "follower": "local_email_unverified_7",
    "followee": "jpop_rap_dance"
  },
  {
    "follower": "local_email_verified_6",
    "followee": "pop_hiphop_vpop"
  },
  {
    "follower": "local_email_verified_7",
    "followee": "local_unverified_3"
  },
  {
    "follower": "inactive_rock",
    "followee": "local_email_unverified_9"
  },
  {
    "follower": "fb_only_active_2",
    "followee": "local_inactive_8"
  },
  {
    "follower": "vpop_indie_pop",
    "followee": "fb_only_inactive_3"
  },
  {
    "follower": "fb_only_inactive_6",
    "followee": "local_locked_2"
  },
  {
    "follower": "local_email_verified",
    "followee": "local_inactive_7"
  },
  {
    "follower": "pop_hiphop_rap",
    "followee": "local_inactive_8"
  },
  {
    "follower": "fb_only_inactive_5",
    "followee": "local_email_verified_8"
  },
  {
    "follower": "pop_vpop_kpop_4",
    "followee": "local_active_3"
  },
  {
    "follower": "local_email_unverified_7",
    "followee": "local_inactive_6"
  },
  {
    "follower": "local_email_verified",
    "followee": "local_email_unverified_6"
  },
  {
    "follower": "rap_hiphop_indie",
    "followee": "user3100"
  },
  {
    "follower": "vpop_indie_pop",
    "followee": "local_email_verified_7"
  },
  {
    "follower": "fb_only_inactive_3",
    "followee": "local_email_verified_7"
  },
  {
    "follower": "fb_only_locked_3",
    "followee": "metalhead"
  },
  {
    "follower": "fb_only_active_3",
    "followee": "jazz_rap_cpop"
  },
  {
    "follower": "moderator_t",
    "followee": "hiphopking"
  },
  {
    "follower": "local_active_4",
    "followee": "local_email_unverified_5"
  },
  {
    "follower": "local_locked_4",
    "followee": "fb_only_active_3"
  },
  {
    "follower": "fb_only_active_2",
    "followee": "fb_only_inactive_4"
  },
  {
    "follower": "rap_hiphop_indie",
    "followee": "local_inactive_8"
  },
  {
    "follower": "fb_only_inactive_4",
    "followee": "pop_vpop_kpop_4"
  },
  {
    "follower": "local_email_unverified_9",
    "followee": "pop_rock_indie"
  },
  {
    "follower": "rap_hiphop_jazz",
    "followee": "fb_only_inactive_2"
  },
  {
    "follower": "hiphop_rap_rock",
    "followee": "pop_dancemix"
  },
  {
    "follower": "local_email_unverified_6",
    "followee": "local_inactive_5"
  }
]